buildstr/__init__.py
buildstr/builder.py
buildstr/builder_test.py
buildstr/builder_test_augass.py
buildstr-0.1.1.dist-info/LICENSE
buildstr-0.1.1.dist-info/METADATA
buildstr-0.1.1.dist-info/WHEEL
buildstr-0.1.1.dist-info/RECORD
