Metadata-Version: 2.1
Name: buildstr
Version: 0.1.1
Summary: Fancy Pythonic String Builder.
Home-page: https://github.com/abilian/buildstr
Author: Abilian SAS
Author-email: sf@abilian.com
Requires-Python: >=3.9,<4.0
Classifier: Development Status :: 2 - Pre-Alpha
Classifier: Intended Audience :: Developers
Classifier: Natural Language :: English
Classifier: Programming Language :: Python :: 3
Classifier: Programming Language :: Python :: 3.9
Classifier: Programming Language :: Python :: 3.10
Classifier: Programming Language :: Python :: 3.11
